s3_scheduler
