Metadata-Version: 2.1
Name: s3-scheduler
Version: 0.0.3
Summary: Use S3 as a scheduler mechanism using Lambda
Home-page: https://github.com/efi-mk/s3-scheduler
Author: Efi Merdler-Kravitz
Author-email: efi.merdler@gmail.com
License: UNKNOWN
Platform: UNKNOWN
Classifier: Programming Language :: Python :: 3
Classifier: License :: OSI Approved :: MIT License
Classifier: Operating System :: OS Independent
